LICENSE.pdf
MANIFEST.in
README.md
README.txt
setup.py
OASYS1_APS_Extensions.egg-info/PKG-INFO
OASYS1_APS_Extensions.egg-info/SOURCES.txt
OASYS1_APS_Extensions.egg-info/dependency_links.txt
OASYS1_APS_Extensions.egg-info/entry_points.txt
OASYS1_APS_Extensions.egg-info/namespace_packages.txt
OASYS1_APS_Extensions.egg-info/not-zip-safe
OASYS1_APS_Extensions.egg-info/requires.txt
OASYS1_APS_Extensions.egg-info/top_level.txt
orangecontrib/__init__.py
orangecontrib/aps/__init__.py
orangecontrib/aps/oasys/__init__.py
orangecontrib/aps/oasys/widgets/__init__.py
orangecontrib/aps/oasys/widgets/error_profile/__init__.py
orangecontrib/aps/oasys/widgets/error_profile/abstract_multiple_height_profile_simulator_S.py
orangecontrib/aps/oasys/widgets/error_profile/abstract_multiple_height_profile_simulator_T.py
orangecontrib/aps/oasys/widgets/extension/__init__.py
orangecontrib/aps/oasys/widgets/extension/ow_scan_file_node_point.py
orangecontrib/aps/oasys/widgets/extension/ow_scan_node_point.py
orangecontrib/aps/oasys/widgets/extension/icons/cycle.png
orangecontrib/aps/oasys/widgets/extension/icons/extension.png
orangecontrib/aps/shadow/__init__.py
orangecontrib/aps/shadow/menu/__init__.py
orangecontrib/aps/shadow/menu/ow_aps_shadow_tools_menu.py
orangecontrib/aps/shadow/util/__init__.py
orangecontrib/aps/shadow/util/gui.py
orangecontrib/aps/shadow/widgets/__init__.py
orangecontrib/aps/shadow/widgets/_not_used/__init__.py
orangecontrib/aps/shadow/widgets/_not_used/hybrid_screen_error_analysis.py
orangecontrib/aps/shadow/widgets/_not_used/ow_aps_hybrid_screen.py
orangecontrib/aps/shadow/widgets/_not_used/ow_aps_undulator_increment.py
orangecontrib/aps/shadow/widgets/_not_used/ow_power_calculator.py
orangecontrib/aps/shadow/widgets/_not_used/ow_power_node_point_old.py
orangecontrib/aps/shadow/widgets/_not_used/ow_power_plot_xy.py
orangecontrib/aps/shadow/widgets/_not_used/ow_preprocessor_adapter.py
orangecontrib/aps/shadow/widgets/_not_used/ow_spectrum_reader.py
orangecontrib/aps/shadow/widgets/_not_used/ow_spectrum_saver.py
orangecontrib/aps/shadow/widgets/_not_used/ow_thickness_file_reader.py
orangecontrib/aps/shadow/widgets/extension/__init__.py
orangecontrib/aps/shadow/widgets/extension/multiple_height_profile_simulator_S.py
orangecontrib/aps/shadow/widgets/extension/multiple_height_profile_simulator_T.py
